Workbook

Sheet 📋 Instructions
B1: PM COMPETENCY QUESTIONNAIRE ASSESSMENT TOOL
B3: 📌 HOW THIS TOOL WORKS
B5: This questionnaire assesses competency through real-world scenarios — NOT by asking you to rate yourself.
B6: You will read 135 situational questions across 8 competency areas. Each question presents a workplace scenario
B7: and 4 possible responses (A, B, C, D). Select the option that BEST describes what you would actually do.
B9: ✅ IMPORTANT RULES FOR EMPLOYEES
B11: • Answer based on what you ACTUALLY do — not what you think the 'correct' answer is.
B12: • There are no trick questions. Your honest responses give the most useful picture.
B13: • Each response option reflects a different level of capability — you will not see scores.
B14: • The questionnaire takes approximately 30–45 minutes to complete.
B15: • Once submitted, scores are calculated automatically in the 'Results' sheet.
B17: 📊 QUESTIONNAIRE STRUCTURE
... B43: for HR/Line Manager use after the questionnaire is submitted.

Sheet 📝 Questionnaire
A1: PROJECT MANAGEMENT COMPETENCY QUESTIONNAIRE
A2: Select the option (A / B / C / D) that BEST describes your typical approach. Answer honestly — there are no right or wrong answers.
A4: Employee Name: | C4: Assessment Date:
A7: 1. ROOT CAUSE ANALYSIS & RISK ASSESSMENT
A9: Q1 | C9: A major project deliverable is consistently late. What is your first step? | D9: YOUR ANSWER ↓
A10: A | C10: A) Ask the team to work overtime to recover the delay | D10: C
A11: B | C11: B) Log the delay in the risk register and notify the sponsor
A12: C | C12: C) Conduct a structured root cause analysis (5-Whys or fishbone) to identify the real driver
A13: D | C13: D) Redesign the project schedule and present a systemic fix with predictive indicators to prevent recurrence
A15: Q2 | C15: During project execution a vendor fails to deliver. How do you respond? | D15: YOUR ANSWER ↓
A16: A | C16: A) Escalate immediately to senior management | D16: B
A17: B | C17: B) Document the issue and investigate the vendor's reason
A18: C | C18: C) Conduct a root cause review, trigger the contingency plan, and adjust the risk register
A19: D | C19: D) Lead a cross-functional risk response, implement lessons-learned and update organisational risk frameworks
A21: Q3 | C21: A risk you identified 3 months ago has now materialised. What does this indicate about your risk approach? | D21: YOUR ANSWER ↓
A22: A | C22: A) Risks are unpredictable; there is nothing more you could have done | D22: C
A23: B | C23: B) The risk register should be updated more frequently
A24: C | C24: C) Proactive monitoring and early-warning indicators were in place but response time needs improvement
A25: D | C25: D) The risk management strategy requires a full review; you implement a real-time risk intelligence system
A27: Q4 | C27: Before a project kicks off, how do you approach risk identification? | D27: YOUR ANSWER ↓
A28: A | C28: A) Wait until risks appear during execution | D28: D
A29: B | C29: B) Use a basic checklist from previous projects
A30: C | C30: C) Facilitate a structured risk workshop using SWOT and probability/impact matrices
A31: D | C31: D) Develop a comprehensive risk taxonomy aligned to organisational strategy with Monte Carlo simulations
A33: Q5 | C33: A key technical assumption in your project is challenged by a stakeholder late in planning. What do you do? | D33: YOUR ANSWER ↓
A34: A | C34: A) Dismiss it since planning is already done | D34: B
A35: B | C35: B) Log it as an issue and note it for later review
A36: C | C36: C) Re-evaluate the assumption formally, update the risk register, and communicate impact to the team
A37: D | C37: D) Integrate assumption management into project governance and present scenario analysis to leadership
A39: Q6 | C39: What best describes how you prevent project failure proactively? | D39: YOUR ANSWER ↓
A40: A | C40: A) React to problems as they arise | D40: D
A41: B | C41: B) Review lessons learned from past projects before starting a new one
A42: C | C42: C) Build pre-mortems, stress tests, and early warning dashboards into every project plan
A43: D | C43: D) Lead organisational failure prevention programmes and embed risk intelligence in project culture
A45: Q7 | C45: A scope change request arrives mid-project. How do you assess its impact? | D45: YOUR ANSWER ↓
A46: A | C46: A) Accept the change if the client requests it | D46: A
A47: B | C47: B) Informally discuss impact with the project team
A48: C | C48: C) Conduct an integrated impact analysis covering cost, time, quality, and risks; update all affected plans
A49: D | C49: D) Develop a strategic impact model linking scope changes to portfolio-level risks and executive decision frameworks
A51: Q8 | C51: Two project risks appear to be interdependent. What do you do? | D51: YOUR ANSWER ↓
A52: A | C52: A) Treat them as separate items in the risk register | D52: B
A53: B | C53: B) Flag the link in a comment and monitor both
A54: C | C54: C) Conduct an integrated risk analysis to assess compounding effects and update mitigation strategies
A55: D | C55: D) Build a risk dependency map for the full project and present it as part of the portfolio risk review
A57: Q9 | C57: When presenting a project risk report to leadership, what does your report typically include? | D57: YOUR ANSWER ↓
A58: A | C58: A) A simple list of current risks | D58: B
A59: B | C59: B) Risk descriptions with probability and impact ratings
A60: C | C60: C) Risk heat maps, trend analysis, and integrated cost-schedule risk impact summaries
A61: D | C61: D) Predictive analytics, scenario planning, and strategic risk response recommendations aligned to business objectives
A63: Q10 | C63: How do you ensure your project can withstand unexpected disruptions? | D63: YOUR ANSWER ↓
A64: A | C64: A) Hope that disruptions do not occur | D64: A
A65: B | C65: B) Keep a list of backup resources
A66: C | C66: C) Develop a resilience plan with contingency budgets, alternative suppliers, and tested recovery procedures
A67: D | C67: D) Lead enterprise resilience planning, embedding operational continuity into project and organisational governance
A69: Q11 | C69: A critical team member suddenly leaves mid-project. What action shows the best resilience approach? | D69: YOUR ANSWER ↓
A70: A | C70: A) Pause the project until a replacement is found | D70: D
A71: B | C71: B) Redistribute tasks among remaining team members
A72: C | C72: C) Activate a pre-planned succession/knowledge transfer plan and re-baseline the schedule
A73: D | C73: D) The departure is managed seamlessly because cross-training and succession plans were built in from day one
A75: Q12 | C75: How frequently do you review operational risks during a project? | D75: YOUR ANSWER ↓
A76: A | C76: A) Only when a problem occurs | D76: A
A77: B | C77: B) At monthly project status meetings
A78: C | C78: C) Weekly, using leading indicators and a dynamic risk register updated by the whole team
A79: D | C79: D) Continuously through an automated risk monitoring system that triggers alerts and board-level dashboards
A81: Q13 | C81: How do you align project risk strategy with organisational strategy? | D81: YOUR ANSWER ↓
A82: A | C82: A) I focus on project risks only; strategy is leadership's responsibility | D82: C
A83: B | C83: B) I share risk reports with leadership when asked
A84: C | C84: C) I ensure project risk appetite is defined in line with organisational strategy and communicated to the team
A85: D | C85: D) I shape enterprise risk strategy, influencing how the organisation approaches risk at portfolio and board level
A87: Q14 | C87: A new emerging technology could either significantly benefit or threaten your project. What do you do? | D87: YOUR ANSWER ↓
A88: A | C88: A) Avoid it until it is more established | D88: C
A89: B | C89: B) Research it and note it as a potential risk
A90: C | C90: C) Conduct a structured innovation risk assessment and present a balanced recommendation to stakeholders
A91: D | C91: D) Lead the evaluation, build a business case, and drive the adoption or mitigation decision at executive level
A93: Q15 | C93: What best describes your approach to risk innovation within your team? | D93: YOUR ANSWER ↓
A94: A | C94: A) Risk management is a compliance requirement; I complete the forms | D94: D
A95: B | C95: B) I encourage team members to raise risks
A96: C | C96: C) I foster a risk-aware culture with regular workshops and reward proactive risk identification
A97: D | C97: D) I mentor the organisation in risk innovation, developing new methodologies and publishing internal best practices
A100: 2. STAKEHOLDER & CONTRACT MANAGEMENT
A102: Q16 | C102: A senior stakeholder changes their position on a key project requirement. What do you do? | D102: YOUR ANSWER ↓
A103: A | C103: A) Accept the change and inform the team
A104: B | C104: B) Document the change and seek approval from the sponsor
A105: C | C105: C) Conduct a stakeholder impact analysis, update the engagement plan, and negotiate a formal change order
A106: D | C106: D) Use the change to re-align project governance frameworks and update the contract management strategy
A108: Q17 | C108: How do you ensure contracts remain aligned with project objectives throughout delivery? | D108: YOUR ANSWER ↓
A109: A | C109: A) Review the contract only if a dispute arises
A110: B | C110: B) Check key contract milestones at project meetings
A111: C | C111: C) Maintain a contract compliance tracker and conduct regular governance reviews with the legal team
A112: D | C112: D) Design and lead contract governance processes that embed compliance into all project decisions and vendor relationships
A114: Q18 | C114: A contractor is underperforming against contract KPIs. What is your first course of action? | D114: YOUR ANSWER ↓
A115: A | C115: A) Give the contractor more time to improve
A116: B | C116: B) Issue a written warning and document the non-compliance
A117: C | C117: C) Initiate a formal performance review, invoke contractual remedies, and escalate through governance channels
A118: D | C118: D) Lead a strategic vendor partnership review and present findings to the executive committee
A120: Q19 | C120: Two key stakeholders have opposing views on project priorities. How do you handle this? | D120: YOUR ANSWER ↓
A121: A | C121: A) Let the project sponsor decide
A122: B | C122: B) Hold separate meetings with each to understand their positions
A123: C | C123: C) Facilitate a structured negotiation session, identify shared interests, and agree a priority framework
A124: D | C124: D) Design a stakeholder alignment process that systematically resolves conflicts and prevents escalation across the programme
...

Sheet 📊 Results & Competency Map
A1: PM COMPETENCY QUESTIONNAIRE — RESULTS & COMPETENCY MAP
A2: Auto-calculated from questionnaire responses | Competency Scale: 1=Amateur 2=Collaborator 3=Enabler 4=Driving Force
A4: # | B4: Sub-Code | C4: Sub-Competency Name | D4: Competency Area | E4: Q1 Score | F4: Q2 Score | G4: Q3 Score | H4: Avg Score | I4: Competency Level
A6: 1. Root Cause Analysis & Risk Assessment
A7: 1 | B7: 1.1 | C7: Root Cause & Risk Management Mastery | D7: Root Cause Analysis & Risk Assessment | E7: =IFERROR(CHOOSE(MATCH('📝 Questionnaire'!D10,{"A","B","C","D"},0),1,2,3,4),"") -> 3 | F7: =IFERROR(CHOOSE(MATCH('📝 Questionnaire'!D16,{"A","B","C","D"},0),1,2,3,4),"") -> 2 | G7: =IFERROR(CHOOSE(MATCH('📝 Questionnaire'!D22,{"A","B","C","D"},0),1,2,3,4),"") -> 3 | H7: =IFERROR(ROUND(AVERAGE(E7:G7),1),"") -> 2.7 | I7: =IF(H7="","",IF(H7<1.5,"1 – Amateur",IF(H7<2.5,"2 – Collaborator",IF(H7<3.5,"3 – Enabler","4 – Driving Force")))) -> 3 – Enabler
A8: 2 | B8: 1.2 | C8: Strategic Risk & Failure Prevention | D8: Root Cause Analysis & Risk Assessment | E8: =IFERROR(CHOOSE(MATCH('📝 Questionnaire'!D28,{"A","B","C","D"},0),1,2,3,4),"") -> 4 | F8: =IFERROR(CHOOSE(MATCH('📝 Questionnaire'!D34,{"A","B","C","D"},0),1,2,3,4),"") -> 2 | G8: =IFERROR(CHOOSE(MATCH('📝 Questionnaire'!D40,{"A","B","C","D"},0),1,2,3,4),"") -> 4 | H8: =IFERROR(ROUND(AVERAGE(E8:G8),1),"") -> 3.3 | I8: =IF(H8="","",IF(H8<1.5,"1 – Amateur",IF(H8<2.5,"2 – Collaborator",IF(H8<3.5,"3 – Enabler","4 – Driving Force")))) -> 3 – Enabler
A9: 3 | B9: 1.3 | C9: Integrated Risk & Impact Analysis | D9: Root Cause Analysis & Risk Assessment | E9: =IFERROR(CHOOSE(MATCH('📝 Questionnaire'!D46,{"A","B","C","D"},0),1,2,3,4),"") -> 1 | F9: =IFERROR(CHOOSE(MATCH('📝 Questionnaire'!D52,{"A","B","C","D"},0),1,2,3,4),"") -> 2 | G9: =IFERROR(CHOOSE(MATCH('📝 Questionnaire'!D58,{"A","B","C","D"},0),1,2,3,4),"") -> 2 | H9: =IFERROR(ROUND(AVERAGE(E9:G9),1),"") -> 1.7 | I9: =IF(H9="","",IF(H9<1.5,"1 – Amateur",IF(H9<2.5,"2 – Collaborator",IF(H9<3.5,"3 – Enabler","4 – Driving Force")))) -> 2 – Collaborator
A10: 4 | B10: 1.4 | C10: Proactive Risk & Operational Resilience | D10: Root Cause Analysis & Risk Assessment | E10: =IFERROR(CHOOSE(MATCH('📝 Questionnaire'!D64,{"A","B","C","D"},0),1,2,3,4),"") -> 1 | F10: =IFERROR(CHOOSE(MATCH('📝 Questionnaire'!D70,{"A","B","C","D"},0),1,2,3,4),"") -> 4 | G10: =IFERROR(CHOOSE(MATCH('📝 Questionnaire'!D76,{"A","B","C","D"},0),1,2,3,4),"") -> 1 | H10: =IFERROR(ROUND(AVERAGE(E10:G10),1),"") -> 2 | I10: =IF(H10="","",IF(H10<1.5,"1 – Amateur",IF(H10<2.5,"2 – Collaborator",IF(H10<3.5,"3 – Enabler","4 – Driving Force")))) -> 2 – Collaborator
A11: 5 | B11: 1.5 | C11: Executive Risk Strategy & Innovation | D11: Root Cause Analysis & Risk Assessment | E11: =IFERROR(CHOOSE(MATCH('📝 Questionnaire'!D82,{"A","B","C","D"},0),1,2,3,4),"") -> 3 | F11: =IFERROR(CHOOSE(MATCH('📝 Questionnaire'!D88,{"A","B","C","D"},0),1,2,3,4),"") -> 3 | G11: =IFERROR(CHOOSE(MATCH('📝 Questionnaire'!D94,{"A","B","C","D"},0),1,2,3,4),"") -> 4 | H11: =IFERROR(ROUND(AVERAGE(E11:G11),1),"") -> 3.3 | I11: =IF(H11="","",IF(H11<1.5,"1 – Amateur",IF(H11<2.5,"2 – Collaborator",IF(H11<3.5,"3 – Enabler","4 – Driving Force")))) -> 3 – Enabler
A13: 2. Stakeholder & Contract Management
A14: 6 | B14: 2.1 | C14: Stakeholder & Contract Governance | D14: Stakeholder & Contract Management | E14: =IFERROR(CHOOSE(MATCH('📝 Questionnaire'!D103,{"A","B","C","D"},0),1,2,3,4),"") | F14: =IFERROR(CHOOSE(MATCH('📝 Questionnaire'!D109,{"A","B","C","D"},0),1,2,3,4),"") | G14: =IFERROR(CHOOSE(MATCH('📝 Questionnaire'!D115,{"A","B","C","D"},0),1,2,3,4),"") | H14: =IFERROR(ROUND(AVERAGE(E14:G14),1),"") | I14: =IF(H14="","",IF(H14<1.5,"1 – Amateur",IF(H14<2.5,"2 – Collaborator",IF(H14<3.5,"3 – Enabler","4 – Driving Force"))))
A15: 7 | B15: 2.2 | C15: Stakeholder & Contract Negotiation | D15: Stakeholder & Contract Management | E15: =IFERROR(CHOOSE(MATCH('📝 Questionnaire'!D121,{"A","B","C","D"},0),1,2,3,4),"") | F15: =IFERROR(CHOOSE(MATCH('📝 Questionnaire'!D127,{"A","B","C","D"},0),1,2,3,4),"") | G15: =IFERROR(CHOOSE(MATCH('📝 Questionnaire'!D133,{"A","B","C","D"},0),1,2,3,4),"") | H15: =IFERROR(ROUND(AVERAGE(E15:G15),1),"") | I15: =IF(H15="","",IF(H15<1.5,"1 – Amateur",IF(H15<2.5,"2 – Collaborator",IF(H15<3.5,"3 – Enabler","4 – Driving Force"))))
A16: 8 | B16: 2.3 | C16: Stakeholder-Centric Contract Governance | D16: Stakeholder & Contract Management | E16: =IFERROR(CHOOSE(MATCH('📝 Questionnaire'!D139,{"A","B","C","D"},0),1,2,3,4),"") | F16: =IFERROR(CHOOSE(MATCH('📝 Questionnaire'!D145,{"A","B","C","D"},0),1,2,3,4),"") | G16: =IFERROR(CHOOSE(MATCH('📝 Questionnaire'!D151,{"A","B","C","D"},0),1,2,3,4),"") | H16: =IFERROR(ROUND(AVERAGE(E16:G16),1),"") | I16: =IF(H16="","",IF(H16<1.5,"1 – Amateur",IF(H16<2.5,"2 – Collaborator",IF(H16<3.5,"3 – Enabler","4 – Driving Force"))))
A17: 9 | B17: 2.4 | C17: Strategic Contract Compliance | D17: Stakeholder & Contract Management | E17: =IFERROR(CHOOSE(MATCH('📝 Questionnaire'!D157,{"A","B","C","D"},0),1,2,3,4),"") | F17: =IFERROR(CHOOSE(MATCH('📝 Questionnaire'!D163,{"A","B","C","D"},0),1,2,3,4),"") | G17: =IFERROR(CHOOSE(MATCH('📝 Questionnaire'!D169,{"A","B","C","D"},0),1,2,3,4),"") | H17: =IFERROR(ROUND(AVERAGE(E17:G17),1),"") | I17: =IF(H17="","",IF(H17<1.5,"1 – Amateur",IF(H17<2.5,"2 – Collaborator",IF(H17<3.5,"3 – Enabler","4 – Driving Force"))))
A18: 10 | B18: 2.5 | C18: Ethical Stakeholder Leadership | D18: Stakeholder & Contract Management | E18: =IFERROR(CHOOSE(MATCH('📝 Questionnaire'!D175,{"A","B","C","D"},0),1,2,3,4),"") | F18: =IFERROR(CHOOSE(MATCH('📝 Questionnaire'!D181,{"A","B","C","D"},0),1,2,3,4),"") | G18: =IFERROR(CHOOSE(MATCH('📝 Questionnaire'!D187,{"A","B","C","D"},0),1,2,3,4),"") | H18: =IFERROR(ROUND(AVERAGE(E18:G18),1),"") | I18: =IF(H18="","",IF(H18<1.5,"1 – Amateur",IF(H18<2.5,"2 – Collaborator",IF(H18<3.5,"3 – Enabler","4 – Driving Force"))))
A19: 11 | B19: 2.6 | C19: Stakeholder & Contract Performance | D19: Stakeholder & Contract Management | E19: =IFERROR(CHOOSE(MATCH('📝 Questionnaire'!D193,{"A","B","C","D"},0),1,2,3,4),"") | F19: =IFERROR(CHOOSE(MATCH('📝 Questionnaire'!D199,{"A","B","C","D"},0),1,2,3,4),"") | G19: =IFERROR(CHOOSE(MATCH('📝 Questionnaire'!D205,{"A","B","C","D"},0),1,2,3,4),"") | H19: =IFERROR(ROUND(AVERAGE(E19:G19),1),"") | I19: =IF(H19="","",IF(H19<1.5,"1 – Amateur",IF(H19<2.5,"2 – Collaborator",IF(H19<3.5,"3 – Enabler","4 – Driving Force"))))
A21: 3. Project Planning & Execution
A22: 12 | B22: 3.1 | C22: Enterprise Project Strategy & Execution | D22: Project Planning & Execution | E22: =IFERROR(CHOOSE(MATCH('📝 Questionnaire'!D214,{"A","B","C","D"},0),1,2,3,4),"") | F22: =IFERROR(CHOOSE(MATCH('📝 Questionnaire'!D220,{"A","B","C","D"},0),1,2,3,4),"") | G22: =IFERROR(CHOOSE(MATCH('📝 Questionnaire'!D226,{"A","B","C","D"},0),1,2,3,4),"") | H22: =IFERROR(ROUND(AVERAGE(E22:G22),1),"") | I22: =IF(H22="","",IF(H22<1.5,"1 – Amateur",IF(H22<2.5,"2 – Collaborator",IF(H22<3.5,"3 – Enabler","4 – Driving Force"))))
A23: 13 | B23: 3.2 | C23: Strategic Project Planning & Optimization | D23: Project Planning & Execution | E23: =IFERROR(CHOOSE(MATCH('📝 Questionnaire'!D232,{"A","B","C","D"},0),1,2,3,4),"") | F23: =IFERROR(CHOOSE(MATCH('📝 Questionnaire'!D238,{"A","B","C","D"},0),1,2,3,4),"") | G23: =IFERROR(CHOOSE(MATCH('📝 Questionnaire'!D244,{"A","B","C","D"},0),1,2,3,4),"") | H23: =IFERROR(ROUND(AVERAGE(E23:G23),1),"") | I23: =IF(H23="","",IF(H23<1.5,"1 – Amateur",IF(H23<2.5,"2 – Collaborator",IF(H23<3.5,"3 – Enabler","4 – Driving Force"))))
A24: 14 | B24: 3.3 | C24: Project Governance & Compliance | D24: Project Planning & Execution | E24: =IFERROR(CHOOSE(MATCH('📝 Questionnaire'!D250,{"A","B","C","D"},0),1,2,3,4),"") | F24: =IFERROR(CHOOSE(MATCH('📝 Questionnaire'!D256,{"A","B","C","D"},0),1,2,3,4),"") | G24: =IFERROR(CHOOSE(MATCH('📝 Questionnaire'!D262,{"A","B","C","D"},0),1,2,3,4),"") | H24: =IFERROR(ROUND(AVERAGE(E24:G24),1),"") | I24: =IF(H24="","",IF(H24<1.5,"1 – Amateur",IF(H24<2.5,"2 – Collaborator",IF(H24<3.5,"3 – Enabler","4 – Driving Force"))))
A25: 15 | B25: 3.4 | C25: Project Monitoring & Refinement | D25: Project Planning & Execution | E25: =IFERROR(CHOOSE(MATCH('📝 Questionnaire'!D268,{"A","B","C","D"},0),1,2,3,4),"") | F25: =IFERROR(CHOOSE(MATCH('📝 Questionnaire'!D274,{"A","B","C","D"},0),1,2,3,4),"") | G25: =IFERROR(CHOOSE(MATCH('📝 Questionnaire'!D280,{"A","B","C","D"},0),1,2,3,4),"") | H25: =IFERROR(ROUND(AVERAGE(E25:G25),1),"") | I25: =IF(H25="","",IF(H25<1.5,"1 – Amateur",IF(H25<2.5,"2 – Collaborator",IF(H25<3.5,"3 – Enabler","4 – Driving Force"))))
A26: 16 | B26: 3.5 | C26: Cross-Functional Project Leadership | D26: Project Planning & Execution | E26: =IFERROR(CHOOSE(MATCH('📝 Questionnaire'!D286,{"A","B","C","D"},0),1,2,3,4),"") | F26: =IFERROR(CHOOSE(MATCH('📝 Questionnaire'!D292,{"A","B","C","D"},0),1,2,3,4),"") | G26: =IFERROR(CHOOSE(MATCH('📝 Questionnaire'!D298,{"A","B","C","D"},0),1,2,3,4),"") | H26: =IFERROR(ROUND(AVERAGE(E26:G26),1),"") | I26: =IF(H26="","",IF(H26<1.5,"1 – Amateur",IF(H26<2.5,"2 – Collaborator",IF(H26<3.5,"3 – Enabler","4 – Driving Force"))))
A28: 4. Proposal Development & Internal Coordination
A29: 17 | B29: 4.1 | C29: Proposal Development & Governance | D29: Proposal Development & Internal Coordination | E29: =IFERROR(CHOOSE(MATCH('📝 Questionnaire'!D307,{"A","B","C","D"},0),1,2,3,4),"") | F29: =IFERROR(CHOOSE(MATCH('📝 Questionnaire'!D313,{"A","B","C","D"},0),1,2,3,4),"") | G29: =IFERROR(CHOOSE(MATCH('📝 Questionnaire'!D319,{"A","B","C","D"},0),1,2,3,4),"") | H29: =IFERROR(ROUND(AVERAGE(E29:G29),1),"") | I29: =IF(H29="","",IF(H29<1.5,"1 – Amateur",IF(H29<2.5,"2 – Collaborator",IF(H29<3.5,"3 – Enabler","4 – Driving Force"))))
A30: 18 | B30: 4.2 | C30: Proposal Alignment & Optimization | D30: Proposal Development & Internal Coordination | E30: =IFERROR(CHOOSE(MATCH('📝 Questionnaire'!D325,{"A","B","C","D"},0),1,2,3,4),"") | F30: =IFERROR(CHOOSE(MATCH('📝 Questionnaire'!D331,{"A","B","C","D"},0),1,2,3,4),"") | G30: =IFERROR(CHOOSE(MATCH('📝 Questionnaire'!D337,{"A","B","C","D"},0),1,2,3,4),"") | H30: =IFERROR(ROUND(AVERAGE(E30:G30),1),"") | I30: =IF(H30="","",IF(H30<1.5,"1 – Amateur",IF(H30<2.5,"2 – Collaborator",IF(H30<3.5,"3 – Enabler","4 – Driving Force"))))
A31: 19 | B31: 4.3 | C31: Communication & Negotiation Excellence | D31: Proposal Development & Internal Coordination | E31: =IFERROR(CHOOSE(MATCH('📝 Questionnaire'!D343,{"A","B","C","D"},0),1,2,3,4),"") | F31: =IFERROR(CHOOSE(MATCH('📝 Questionnaire'!D349,{"A","B","C","D"},0),1,2,3,4),"") | G31: =IFERROR(CHOOSE(MATCH('📝 Questionnaire'!D355,{"A","B","C","D"},0),1,2,3,4),"") | H31: =IFERROR(ROUND(AVERAGE(E31:G31),1),"") | I31: =IF(H31="","",IF(H31<1.5,"1 – Amateur",IF(H31<2.5,"2 – Collaborator",IF(H31<3.5,"3 – Enabler","4 – Driving Force"))))
A32: 20 | B32: 4.4 | C32: Proposal Governance Strategy | D32: Proposal Development & Internal Coordination | E32: =IFERROR(CHOOSE(MATCH('📝 Questionnaire'!D361,{"A","B","C","D"},0),1,2,3,4),"") | F32: =IFERROR(CHOOSE(MATCH('📝 Questionnaire'!D367,{"A","B","C","D"},0),1,2,3,4),"") | G32: =IFERROR(CHOOSE(MATCH('📝 Questionnaire'!D373,{"A","B","C","D"},0),1,2,3,4),"") | H32: =IFERROR(ROUND(AVERAGE(E32:G32),1),"") | I32: =IF(H32="","",IF(H32<1.5,"1 – Amateur",IF(H32<2.5,"2 – Collaborator",IF(H32<3.5,"3 – Enabler","4 – Driving Force"))))
A33: 21 | B33: 4.5 | C33: Proposal Excellence & Impact | D33: Proposal Development & Internal Coordination | E33: =IFERROR(CHOOSE(MATCH('📝 Questionnaire'!D379,{"A","B","C","D"},0),1,2,3,4),"") | F33: =IFERROR(CHOOSE(MATCH('📝 Questionnaire'!D385,{"A","B","C","D"},0),1,2,3,4),"") | G33: =IFERROR(CHOOSE(MATCH('📝 Questionnaire'!D391,{"A","B","C","D"},0),1,2,3,4),"") | H33: =IFERROR(ROUND(AVERAGE(E33:G33),1),"") | I33: =IF(H33="","",IF(H33<1.5,"1 – Amateur",IF(H33<2.5,"2 – Collaborator",IF(H33<3.5,"3 – Enabler","4 – Driving Force"))))
A35: 5. Resource Management & Budget Control
A36: 22 | B36: 5.1 | C36: Enterprise Budgeting & Resource Optimization | D36: Resource Management & Budget Control | E36: =IFERROR(CHOOSE(MATCH('📝 Questionnaire'!D400,{"A","B","C","D"},0),1,2,3,4),"") | F36: =IFERROR(CHOOSE(MATCH('📝 Questionnaire'!D406,{"A","B","C","D"},0),1,2,3,4),"") | G36: =IFERROR(CHOOSE(MATCH('📝 Questionnaire'!D412,{"A","B","C","D"},0),1,2,3,4),"") | H36: =IFERROR(ROUND(AVERAGE(E36:G36),1),"") | I36: =IF(H36="","",IF(H36<1.5,"1 – Amateur",IF(H36<2.5,"2 – Collaborator",IF(H36<3.5,"3 – Enabler","4 – Driving Force"))))
A37: 23 | B37: 5.2 | C37: Financial Compliance & Resource Governance | D37: Resource Management & Budget Control | E37: =IFERROR(CHOOSE(MATCH('📝 Questionnaire'!D418,{"A","B","C","D"},0),1,2,3,4),"") | F37: =IFERROR(CHOOSE(MATCH('📝 Questionnaire'!D424,{"A","B","C","D"},0),1,2,3,4),"") | G37: =IFERROR(CHOOSE(MATCH('📝 Questionnaire'!D430,{"A","B","C","D"},0),1,2,3,4),"") | H37: =IFERROR(ROUND(AVERAGE(E37:G37),1),"") | I37: =IF(H37="","",IF(H37<1.5,"1 – Amateur",IF(H37<2.5,"2 – Collaborator",IF(H37<3.5,"3 – Enabler","4 – Driving Force"))))
A38: 24 | B38: 5.3 | C38: Financial Automation & Optimization | D38: Resource Management & Budget Control | E38: =IFERROR(CHOOSE(MATCH('📝 Questionnaire'!D436,{"A","B","C","D"},0),1,2,3,4),"") | F38: =IFERROR(CHOOSE(MATCH('📝 Questionnaire'!D442,{"A","B","C","D"},0),1,2,3,4),"") | G38: =IFERROR(CHOOSE(MATCH('📝 Questionnaire'!D448,{"A","B","C","D"},0),1,2,3,4),"") | H38: =IFERROR(ROUND(AVERAGE(E38:G38),1),"") | I38: =IF(H38="","",IF(H38<1.5,"1 – Amateur",IF(H38<2.5,"2 – Collaborator",IF(H38<3.5,"3 – Enabler","4 – Driving Force"))))
A39: 25 | B39: 5.4 | C39: Cost Efficiency & Waste Reduction | D39: Resource Management & Budget Control | E39: =IFERROR(CHOOSE(MATCH('📝 Questionnaire'!D454,{"A","B","C","D"},0),1,2,3,4),"") | F39: =IFERROR(CHOOSE(MATCH('📝 Questionnaire'!D460,{"A","B","C","D"},0),1,2,3,4),"") | G39: =IFERROR(CHOOSE(MATCH('📝 Questionnaire'!D466,{"A","B","C","D"},0),1,2,3,4),"") | H39: =IFERROR(ROUND(AVERAGE(E39:G39),1),"") | I39: =IF(H39="","",IF(H39<1.5,"1 – Amateur",IF(H39<2.5,"2 – Collaborator",IF(H39<3.5,"3 – Enabler","4 – Driving Force"))))
A40: 26 | B40: 5.5 | C40: Budget Variance Analysis & Optimization | D40: Resource Management & Budget Control | E40: =IFERROR(CHOOSE(MATCH('📝 Questionnaire'!D472,{"A","B","C","D"},0),1,2,3,4),"") | F40: =IFERROR(CHOOSE(MATCH('📝 Questionnaire'!D478,{"A","B","C","D"},0),1,2,3,4),"") | G40: =IFERROR(CHOOSE(MATCH('📝 Questionnaire'!D484,{"A","B","C","D"},0),1,2,3,4),"") | H40: =IFERROR(ROUND(AVERAGE(E40:G40),1),"") | I40: =IF(H40="","",IF(H40<1.5,"1 – Amateur",IF(H40<2.5,"2 – Collaborator",IF(H40<3.5,"3 – Enabler","4 – Driving Force"))))
A41: 27 | B41: 5.6 | C41: Financial Governance & Resource Optimization | D41: Resource Management & Budget Control | E41: =IFERROR(CHOOSE(MATCH('📝 Questionnaire'!D490,{"A","B","C","D"},0),1,2,3,4),"") | F41: =IFERROR(CHOOSE(MATCH('📝 Questionnaire'!D496,{"A","B","C","D"},0),1,2,3,4),"") | G41: =IFERROR(CHOOSE(MATCH('📝 Questionnaire'!D502,{"A","B","C","D"},0),1,2,3,4),"") | H41: =IFERROR(ROUND(AVERAGE(E41:G41),1),"") | I41: =IF(H41="","",IF(H41<1.5,"1 – Amateur",IF(H41<2.5,"2 – Collaborator",IF(H41<3.5,"3 – Enabler","4 – Driving Force"))))
A43: 6. Digital PM & Technology Innovation
A44: 28 | B44: 6.1 | C44: PM System Optimization | D44: Digital PM & Technology Innovation | E44: =IFERROR(CHOOSE(MATCH('📝 Questionnaire'!D511,{"A","B","C","D"},0),1,2,3,4),"") | F44: =IFERROR(CHOOSE(MATCH('📝 Questionnaire'!D517,{"A","B","C","D"},0),1,2,3,4),"") | G44: =IFERROR(CHOOSE(MATCH('📝 Questionnaire'!D523,{"A","B","C","D"},0),1,2,3,4),"") | H44: =IFERROR(ROUND(AVERAGE(E44:G44),1),"") | I44: =IF(H44="","",IF(H44<1.5,"1 – Amateur",IF(H44<2.5,"2 – Collaborator",IF(H44<3.5,"3 – Enabler","4 – Driving Force"))))
A45: 29 | B45: 6.2 | C45: AI-Driven Digital Efficiency & Automation | D45: Digital PM & Technology Innovation | E45: =IFERROR(CHOOSE(MATCH('📝 Questionnaire'!D529,{"A","B","C","D"},0),1,2,3,4),"") | F45: =IFERROR(CHOOSE(MATCH('📝 Questionnaire'!D535,{"A","B","C","D"},0),1,2,3,4),"") | G45: =IFERROR(CHOOSE(MATCH('📝 Questionnaire'!D541,{"A","B","C","D"},0),1,2,3,4),"") | H45: =IFERROR(ROUND(AVERAGE(E45:G45),1),"") | I45: =IF(H45="","",IF(H45<1.5,"1 – Amateur",IF(H45<2.5,"2 – Collaborator",IF(H45<3.5,"3 – Enabler","4 – Driving Force"))))
A46: 30 | B46: 6.3 | C46: AI-Driven ERP Transformation | D46: Digital PM & Technology Innovation | E46: =IFERROR(CHOOSE(MATCH('📝 Questionnaire'!D547,{"A","B","C","D"},0),1,2,3,4),"") | F46: =IFERROR(CHOOSE(MATCH('📝 Questionnaire'!D553,{"A","B","C","D"},0),1,2,3,4),"") | G46: =IFERROR(CHOOSE(MATCH('📝 Questionnaire'!D559,{"A","B","C","D"},0),1,2,3,4),"") | H46: =IFERROR(ROUND(AVERAGE(E46:G46),1),"") | I46: =IF(H46="","",IF(H46<1.5,"1 – Amateur",IF(H46<2.5,"2 – Collaborator",IF(H46<3.5,"3 – Enabler","4 – Driving Force"))))
A47: 31 | B47: 6.4 | C47: IT Enablement & Digital Innovation | D47: Digital PM & Technology Innovation | E47: =IFERROR(CHOOSE(MATCH('📝 Questionnaire'!D565,{"A","B","C","D"},0),1,2,3,4),"") | F47: =IFERROR(CHOOSE(MATCH('📝 Questionnaire'!D571,{"A","B","C","D"},0),1,2,3,4),"") | G47: =IFERROR(CHOOSE(MATCH('📝 Questionnaire'!D577,{"A","B","C","D"},0),1,2,3,4),"") | H47: =IFERROR(ROUND(AVERAGE(E47:G47),1),"") | I47: =IF(H47="","",IF(H47<1.5,"1 – Amateur",IF(H47<2.5,"2 – Collaborator",IF(H47<3.5,"3 – Enabler","4 – Driving Force"))))
A48: 32 | B48: 6.5 | C48: IT Troubleshooting & Intelligent Automation | D48: Digital PM & Technology Innovation | E48: =IFERROR(CHOOSE(MATCH('📝 Questionnaire'!D583,{"A","B","C","D"},0),1,2,3,4),"") | F48: =IFERROR(CHOOSE(MATCH('📝 Questionnaire'!D589,{"A","B","C","D"},0),1,2,3,4),"") | G48: =IFERROR(CHOOSE(MATCH('📝 Questionnaire'!D595,{"A","B","C","D"},0),1,2,3,4),"") | H48: =IFERROR(ROUND(AVERAGE(E48:G48),1),"") | I48: =IF(H48="","",IF(H48<1.5,"1 – Amateur",IF(H48<2.5,"2 – Collaborator",IF(H48<3.5,"3 – Enabler","4 – Driving Force"))))
A49: 33 | B49: 6.6 | C49: IT Optimization & Automation Strategy | D49: Digital PM & Technology Innovation | E49: =IFERROR(CHOOSE(MATCH('📝 Questionnaire'!D601,{"A","B","C","D"},0),1,2,3,4),"") | F49: =IFERROR(CHOOSE(MATCH('📝 Questionnaire'!D607,{"A","B","C","D"},0),1,2,3,4),"") | G49: =IFERROR(CHOOSE(MATCH('📝 Questionnaire'!D613,{"A","B","C","D"},0),1,2,3,4),"") | H49: =IFERROR(ROUND(AVERAGE(E49:G49),1),"") | I49: =IF(H49="","",IF(H49<1.5,"1 – Amateur",IF(H49<2.5,"2 – Collaborator",IF(H49<3.5,"3 – Enabler","4 – Driving Force"))))
A51: 7. Operations & Sustainability Management
A52: 34 | B52: 7.1 | C52: Outsourced Maintenance & Sustainability | D52: Operations & Sustainability Management | E52: =IFERROR(CHOOSE(MATCH('📝 Questionnaire'!D622,{"A","B","C","D"},0),1,2,3,4),"") | F52: =IFERROR(CHOOSE(MATCH('📝 Questionnaire'!D628,{"A","B","C","D"},0),1,2,3,4),"") | G52: =IFERROR(CHOOSE(MATCH('📝 Questionnaire'!D634,{"A","B","C","D"},0),1,2,3,4),"") | H52: =IFERROR(ROUND(AVERAGE(E52:G52),1),"") | I52: =IF(H52="","",IF(H52<1.5,"1 – Amateur",IF(H52<2.5,"2 – Collaborator",IF(H52<3.5,"3 – Enabler","4 – Driving Force"))))
A53: 35 | B53: 7.2 | C53: Sustainability Integration & Compliance | D53: Operations & Sustainability Management | E53: =IFERROR(CHOOSE(MATCH('📝 Questionnaire'!D640,{"A","B","C","D"},0),1,2,3,4),"") | F53: =IFERROR(CHOOSE(MATCH('📝 Questionnaire'!D646,{"A","B","C","D"},0),1,2,3,4),"") | G53: =IFERROR(CHOOSE(MATCH('📝 Questionnaire'!D652,{"A","B","C","D"},0),1,2,3,4),"") | H53: =IFERROR(ROUND(AVERAGE(E53:G53),1),"") | I53: =IF(H53="","",IF(H53<1.5,"1 – Amateur",IF(H53<2.5,"2 – Collaborator",IF(H53<3.5,"3 – Enabler","4 – Driving Force"))))
A54: 36 | B54: 7.3 | C54: Vendor Governance & Sustainability | D54: Operations & Sustainability Management | E54: =IFERROR(CHOOSE(MATCH('📝 Questionnaire'!D658,{"A","B","C","D"},0),1,2,3,4),"") | F54: =IFERROR(CHOOSE(MATCH('📝 Questionnaire'!D664,{"A","B","C","D"},0),1,2,3,4),"") | G54: =IFERROR(CHOOSE(MATCH('📝 Questionnaire'!D670,{"A","B","C","D"},0),1,2,3,4),"") | H54: =IFERROR(ROUND(AVERAGE(E54:G54),1),"") | I54: =IF(H54="","",IF(H54<1.5,"1 – Amateur",IF(H54<2.5,"2 – Collaborator",IF(H54<3.5,"3 – Enabler","4 – Driving Force"))))
A55: 37 | B55: 7.4 | C55: Sustainable Outsourcing & Digital Efficiency | D55: Operations & Sustainability Management | E55: =IFERROR(CHOOSE(MATCH('📝 Questionnaire'!D676,{"A","B","C","D"},0),1,2,3,4),"") | F55: =IFERROR(CHOOSE(MATCH('📝 Questionnaire'!D682,{"A","B","C","D"},0),1,2,3,4),"") | G55: =IFERROR(CHOOSE(MATCH('📝 Questionnaire'!D688,{"A","B","C","D"},0),1,2,3,4),"") | H55: =IFERROR(ROUND(AVERAGE(E55:G55),1),"") | I55: =IF(H55="","",IF(H55<1.5,"1 – Amateur",IF(H55<2.5,"2 – Collaborator",IF(H55<3.5,"3 – Enabler","4 – Driving Force"))))
A56: 38 | B56: 7.5 | C56: Sustainable Vendor Management & Innovation | D56: Operations & Sustainability Management | E56: =IFERROR(CHOOSE(MATCH('📝 Questionnaire'!D694,{"A","B","C","D"},0),1,2,3,4),"") | F56: =IFERROR(CHOOSE(MATCH('📝 Questionnaire'!D700,{"A","B","C","D"},0),1,2,3,4),"") | G56: =IFERROR(CHOOSE(MATCH('📝 Questionnaire'!D706,{"A","B","C","D"},0),1,2,3,4),"") | H56: =IFERROR(ROUND(AVERAGE(E56:G56),1),"") | I56: =IF(H56="","",IF(H56<1.5,"1 – Amateur",IF(H56<2.5,"2 – Collaborator",IF(H56<3.5,"3 – Enabler","4 – Driving Force"))))
A57: 39 | B57: 7.6 | C57: Maintenance & Vendor Excellence | D57: Operations & Sustainability Management | E57: =IFERROR(CHOOSE(MATCH('📝 Questionnaire'!D712,{"A","B","C","D"},0),1,2,3,4),"") | F57: =IFERROR(CHOOSE(MATCH('📝 Questionnaire'!D718,{"A","B","C","D"},0),1,2,3,4),"") | G57: =IFERROR(CHOOSE(MATCH('📝 Questionnaire'!D724,{"A","B","C","D"},0),1,2,3,4),"") | H57: =IFERROR(ROUND(AVERAGE(E57:G57),1),"") | I57: =IF(H57="","",IF(H57<1.5,"1 – Amateur",IF(H57<2.5,"2 – Collaborator",IF(H57<3.5,"3 – Enabler","4 – Driving Force"))))
A59: 8. Professional Certifications
A60: 40 | B60: 8.1 | C60: Certification Progression & Expertise | D60: Professional Certifications | E60: =IFERROR(CHOOSE(MATCH('📝 Questionnaire'!D733,{"A","B","C","D"},0),1,2,3,4),"") | F60: =IFERROR(CHOOSE(MATCH('📝 Questionnaire'!D739,{"A","B","C","D"},0),1,2,3,4),"") | G60: =IFERROR(CHOOSE(MATCH('📝 Questionnaire'!D745,{"A","B","C","D"},0),1,2,3,4),"") | H60: =IFERROR(ROUND(AVERAGE(E60:G60),1),"") | I60: =IF(H60="","",IF(H60<1.5,"1 – Amateur",IF(H60<2.5,"2 – Collaborator",IF(H60<3.5,"3 – Enabler","4 – Driving Force"))))
A61: 41 | B61: 8.2 | C61: Certification-Driven Project Excellence | D61: Professional Certifications | E61: =IFERROR(CHOOSE(MATCH('📝 Questionnaire'!D751,{"A","B","C","D"},0),1,2,3,4),"") | F61: =IFERROR(CHOOSE(MATCH('📝 Questionnaire'!D757,{"A","B","C","D"},0),1,2,3,4),"") | G61: =IFERROR(CHOOSE(MATCH('📝 Questionnaire'!D763,{"A","B","C","D"},0),1,2,3,4),"") | H61: =IFERROR(ROUND(AVERAGE(E61:G61),1),"") | I61: =IF(H61="","",IF(H61<1.5,"1 – Amateur",IF(H61<2.5,"2 – Collaborator",IF(H61<3.5,"3 – Enabler","4 – Driving Force"))))
A62: 42 | B62: 8.3 | C62: Certification-Based Leadership & Compliance | D62: Professional Certifications | E62: =IFERROR(CHOOSE(MATCH('📝 Questionnaire'!D769,{"A","B","C","D"},0),1,2,3,4),"") | F62: =IFERROR(CHOOSE(MATCH('📝 Questionnaire'!D775,{"A","B","C","D"},0),1,2,3,4),"") | G62: =IFERROR(CHOOSE(MATCH('📝 Questionnaire'!D781,{"A","B","C","D"},0),1,2,3,4),"") | H62: =IFERROR(ROUND(AVERAGE(E62:G62),1),"") | I62: =IF(H62="","",IF(H62<1.5,"1 – Amateur",IF(H62<2.5,"2 – Collaborator",IF(H62<3.5,"3 – Enabler","4 – Driving Force"))))
A63: 43 | B63: 8.4 | C63: Certification-Based Governance & Transformation | D63: Professional Certifications | E63: =IFERROR(CHOOSE(MATCH('📝 Questionnaire'!D787,{"A","B","C","D"},0),1,2,3,4),"") | F63: =IFERROR(CHOOSE(MATCH('📝 Questionnaire'!D793,{"A","B","C","D"},0),1,2,3,4),"") | G63: =IFERROR(CHOOSE(MATCH('📝 Questionnaire'!D799,{"A","B","C","D"},0),1,2,3,4),"") | H63: =IFERROR(ROUND(AVERAGE(E63:G63),1),"") | I63: =IF(H63="","",IF(H63<1.5,"1 – Amateur",IF(H63<2.5,"2 – Collaborator",IF(H63<3.5,"3 – Enabler","4 – Driving Force"))))
A64: 44 | B64: 8.5 | C64: Certification-Driven Continuous Learning | D64: Professional Certifications | E64: =IFERROR(CHOOSE(MATCH('📝 Questionnaire'!D805,{"A","B","C","D"},0),1,2,3,4),"") | F64: =IFERROR(CHOOSE(MATCH('📝 Questionnaire'!D811,{"A","B","C","D"},0),1,2,3,4),"") | G64: =IFERROR(CHOOSE(MATCH('📝 Questionnaire'!D817,{"A","B","C","D"},0),1,2,3,4),"") | H64: =IFERROR(ROUND(AVERAGE(E64:G64),1),"") | I64: =IF(H64="","",IF(H64<1.5,"1 – Amateur",IF(H64<2.5,"2 – Collaborator",IF(H64<3.5,"3 – Enabler","4 – Driving Force"))))
A65: 45 | B65: 8.6 | C65: Certification-Driven Leadership & Strategic Alignment | D65: Professional Certifications | E65: =IFERROR(CHOOSE(MATCH('📝 Questionnaire'!D823,{"A","B","C","D"},0),1,2,3,4),"") | F65: =IFERROR(CHOOSE(MATCH('📝 Questionnaire'!D829,{"A","B","C","D"},0),1,2,3,4),"") | G65: =IFERROR(CHOOSE(MATCH('📝 Questionnaire'!D835,{"A","B","C","D"},0),1,2,3,4),"") | H65: =IFERROR(ROUND(AVERAGE(E65:G65),1),"") | I65: =IF(H65="","",IF(H65<1.5,"1 – Amateur",IF(H65<2.5,"2 – Collaborator",IF(H65<3.5,"3 – Enabler","4 – Driving Force"))))
A67: ★ COMPETENCY AREA SUMMARY
B68: Area # | C68: Competency Area | D68: # Sub-Comps | E68: Avg Q Score | F68: Competency Level | G68: Action
B69: 1 | C69: Root Cause Analysis & Risk Assessment | D69: 5 | E69: =IFERROR(ROUND(AVERAGE(H7,H8,H9,H10,H11),1),"") -> 2.6 | F69: =IF(E69="","",IF(E69<1.5,"1 – Amateur",IF(E69<2.5,"2 – Collaborator",IF(E69<3.5,"3 – Enabler","4 – Driving Force")))) -> 3 – Enabler | G69: =IF(E69="","—",IF(E69>=3.5,"No Action Needed",IF(E69>=2.5,"Targeted Dev Plan",IF(E69>=1.5,"Structured Dev Plan","Urgent Intervention")))) -> Targeted Dev Plan
B70: 2 | C70: Stakeholder & Contract Management | D70: 6 | E70: =IFERROR(ROUND(AVERAGE(H14,H15,H16,H17,H18,H19),1),"") | F70: =IF(E70="","",IF(E70<1.5,"1 – Amateur",IF(E70<2.5,"2 – Collaborator",IF(E70<3.5,"3 – Enabler","4 – Driving Force")))) | G70: =IF(E70="","—",IF(E70>=3.5,"No Action Needed",IF(E70>=2.5,"Targeted Dev Plan",IF(E70>=1.5,"Structured Dev Plan","Urgent Intervention")))) -> —
B71: 3 | C71: Project Planning & Execution | D71: 5 | E71: =IFERROR(ROUND(AVERAGE(H22,H23,H24,H25,H26),1),"") | F71: =IF(E71="","",IF(E71<1.5,"1 – Amateur",IF(E71<2.5,"2 – Collaborator",IF(E71<3.5,"3 – Enabler","4 – Driving Force")))) | G71: =IF(E71="","—",IF(E71>=3.5,"No Action Needed",IF(E71>=2.5,"Targeted Dev Plan",IF(E71>=1.5,"Structured Dev Plan","Urgent Intervention")))) -> —
B72: 4 | C72: Proposal Development & Internal Coordination | D72: 5 | E72: =IFERROR(ROUND(AVERAGE(H29,H30,H31,H32,H33),1),"") | F72: =IF(E72="","",IF(E72<1.5,"1 – Amateur",IF(E72<2.5,"2 – Collaborator",IF(E72<3.5,"3 – Enabler","4 – Driving Force")))) | G72: =IF(E72="","—",IF(E72>=3.5,"No Action Needed",IF(E72>=2.5,"Targeted Dev Plan",IF(E72>=1.5,"Structured Dev Plan","Urgent Intervention")))) -> —
B73: 5 | C73: Resource Management & Budget Control | D73: 6 | E73: =IFERROR(ROUND(AVERAGE(H36,H37,H38,H39,H40,H41),1),"") | F73: =IF(E73="","",IF(E73<1.5,"1 – Amateur",IF(E73<2.5,"2 – Collaborator",IF(E73<3.5,"3 – Enabler","4 – Driving Force")))) | G73: =IF(E73="","—",IF(E73>=3.5,"No Action Needed",IF(E73>=2.5,"Targeted Dev Plan",IF(E73>=1.5,"Structured Dev Plan","Urgent Intervention")))) -> —
B74: 6 | C74: Digital PM & Technology Innovation | D74: 6 | E74: =IFERROR(ROUND(AVERAGE(H44,H45,H46,H47,H48,H49),1),"") | F74: =IF(E74="","",IF(E74<1.5,"1 – Amateur",IF(E74<2.5,"2 – Collaborator",IF(E74<3.5,"3 – Enabler","4 – Driving Force")))) | G74: =IF(E74="","—",IF(E74>=3.5,"No Action Needed",IF(E74>=2.5,"Targeted Dev Plan",IF(E74>=1.5,"Structured Dev Plan","Urgent Intervention")))) -> —
B75: 7 | C75: Operations & Sustainability Management | D75: 6 | E75: =IFERROR(ROUND(AVERAGE(H52,H53,H54,H55,H56,H57),1),"") | F75: =IF(E75="","",IF(E75<1.5,"1 – Amateur",IF(E75<2.5,"2 – Collaborator",IF(E75<3.5,"3 – Enabler","4 – Driving Force")))) | G75: =IF(E75="","—",IF(E75>=3.5,"No Action Needed",IF(E75>=2.5,"Targeted Dev Plan",IF(E75>=1.5,"Structured Dev Plan","Urgent Intervention")))) -> —
B76: 8 | C76: Professional Certifications | D76: 6 | E76: =IFERROR(ROUND(AVERAGE(H60,H61,H62,H63,H64,H65),1),"") | F76: =IF(E76="","",IF(E76<1.5,"1 – Amateur",IF(E76<2.5,"2 – Collaborator",IF(E76<3.5,"3 – Enabler","4 – Driving Force")))) | G76: =IF(E76="","—",IF(E76>=3.5,"No Action Needed",IF(E76>=2.5,"Targeted Dev Plan",IF(E76>=1.5,"Structured Dev Plan","Urgent Intervention")))) -> —
B77: ★ | C77: OVERALL QUESTIONNAIRE COMPETENCY SCORE | E77: =IFERROR(ROUND(AVERAGE(E69:E76),1),"") -> 2.6 | F77: =IF(E77="","",IF(E77<1.5,"1 – Amateur",IF(E77<2.5,"2 – Collaborator",IF(E77<3.5,"3 – Enabler","4 – Driving Force")))) -> 3 – Enabler
